{
  "NTProvider": {
    "types": {
      "/FMSInfo": "FMSInfo",
      "/SmartDashboard/Elevator Sim": "Mechanism2d"
    },
    "windows": {
      "/SmartDashboard/Elevator Sim": {
        "window": {
          "visible": true
        }
      }
    }
  },
  "NetworkTables": {
    "transitory": {
      "Shuffleboard": {
        "open": true
      },
      "SmartDashboard": {
        "Elevator Sim": {
          "double[]##v_/SmartDashboard/Elevator Sim/dims": {
            "open": true
          },
          "open": true
        },
        "open": true
      }
    }
  },
  "NetworkTables Info": {
    "visible": true
  }
}
